dt_tools/cli/dt_tools_help_cli.py
dt_tools/cli/ip_helper_cli.py
dt_tools/cli/lan_clients_cli.py
dt_tools/cli/port_check_cli.py
dt_tools/cli/sound_gauge_cli.py
dt_tools/cli/speak_cli.py
dt_tools/cli/weather_cli.py
dt_tools/cli/what_time_cli.py
dt_tools/cli/wol_cli.py
dt_cli_tools-0.1.38.dist-info/entry_points.txt
dt_cli_tools-0.1.38.dist-info/LICENSE
dt_cli_tools-0.1.38.dist-info/METADATA
dt_cli_tools-0.1.38.dist-info/WHEEL
dt_cli_tools-0.1.38.dist-info/RECORD
