Metadata-Version: 2.3
Name: dt-cli-tools
Version: 0.1.38
Summary: Various CLIs created from dt-* packages
License: MIT
Keywords: python,dt-tools,network
Author: Al DAmico
Author-email: JavaWiz1@hotmail.com
Requires-Python: >=3.10,<4.0
Classifier: License :: OSI Approved :: MIT License
Classifier: Programming Language :: Python
Classifier: Programming Language :: Python :: 3
Classifier: Programming Language :: Python :: 3.10
Classifier: Programming Language :: Python :: 3.11
Classifier: Programming Language :: Python :: 3.12
Classifier: Programming Language :: Python :: 3.13
Requires-Dist: dataclasses-json
Requires-Dist: dt-console
Requires-Dist: dt-foundation
Requires-Dist: dt-misc
Requires-Dist: dt-net
Project-URL: Repository, https://github.com/JavaWiz1/dt-cli-tools
